pymodore.py
pymodore-1.1.0.dist-info/LICENSE
pymodore-1.1.0.dist-info/METADATA
pymodore-1.1.0.dist-info/WHEEL
pymodore-1.1.0.dist-info/entry_points.txt
pymodore-1.1.0.dist-info/top_level.txt
pymodore-1.1.0.dist-info/RECORD
